JK/JK.vhdl
library IEEE;
use IEEE.STD_LOGIC_1164.ALL;
use IEEE.NUMERIC_STD.ALL;

entity JK is
    Port(J, K, CLK, RST : IN STD_LOGIC;
         Q, Qn : OUT STD_LOGIC);
end JK;

architecture BehavioralModel of JK is
    signal Q_reg, Qn_reg : STD_LOGIC;
begin
    process(J,K,CLK,RST)
    begin
        if(RST = '1') then
            Q_reg <= '0';
            Qn_reg <= '1';
    
        elsif rising_edge(CLK) then
            if (J = '0' and K = '0') then
                Q_reg <= Q_reg;
                Qn_reg <= Qn_reg;


            elsif (J = '0' and K = '1') then
                Q_reg <= '0';
                Qn_reg <= '1';


            elsif (J = '1' and K = '0') then
                Q_reg <= '1';
                Qn_reg <= '0';

            elsif (J = '1' and K = '1') then
                Q_reg <= not Q_reg;
                Qn_reg <= not Qn_reg;
            end if;
        end if;
        Q <= Q_reg;
        Qn <= Qn_reg;
    end process;

end BehavioralModel;

JK/JK_tb.vhdl
library IEEE;
use IEEE.STD_LOGIC_1164.ALL;
use IEEE.NUMERIC_STD.ALL;

entity JK_tb is
end JK_tb;

architecture Simulation1 of JK_tb is

    signal J_tb, K_tb, CLK_tb, RST_tb : STD_LOGIC;
    signal Q_tb, Qn_tb : STD_LOGIC;

begin
    JK_Instance : entity work.JK PORT MAP(J_tb, K_tb, CLK_tb, RST_tb, Q_tb, Qn_tb);

    Clock_Process: process
    begin
        while now < 100 ns loop
            CLK_tb <= '1';
            wait for 5 ns;
            CLK_tb <= '0';
            wait for 5 ns;
        end loop;
        wait;
    end process;

    AStimulus_Reset_Process : process
    begin

        RST_tb <= '0';
        J_tb <= '0';
        K_tb <='0';
        wait for 15 ns;


        RST_tb <= '0';
        J_tb <= '0';
        K_tb <='1';
        wait for 15 ns;

        RST_tb <= '0';
        J_tb <= '1';
        K_tb <='0';
        wait for 15 ns;

        RST_tb <= '0';
        J_tb <= '1';
        K_tb <='1';
        wait for 15 ns;

        RST_tb <= '1';
        J_tb <= '1';
        K_tb <='0';
        wait for 15 ns;

        RST_tb <= '1';
        J_tb <= '1';
        K_tb <='0';
        wait for 15 ns;

        wait;
    end process;

end Simulation1;

JK/result.vcd
$date
  Sat Feb 10 17:37:50 2024
$end
$version
  GHDL v0
$end
$timescale
  1 fs
$end
$scope module standard $end
$upscope $end
$scope module std_logic_1164 $end
$upscope $end
$scope module numeric_std $end
$upscope $end
$scope module jk_tb $end
$var reg 1 ! j_tb $end
$var reg 1 " k_tb $end
$var reg 1 # clk_tb $end
$var reg 1 $ rst_tb $end
$var reg 1 % q_tb $end
$var reg 1 & qn_tb $end
$scope module jk_instance $end
$var reg 1 ' j $end
$var reg 1 ( k $end
$var reg 1 ) clk $end
$var reg 1 * rst $end
$var reg 1 + q $end
$var reg 1 , qn $end
$var reg 1 - q_reg $end
$var reg 1 . qn_reg $end
$upscope $end
$upscope $end
$enddefinitions $end
#0
0!
0"
1#
0$
U%
U&
0'
0(
1)
0*
U+
U,
U-
U.
#5000000
0#
0)
#10000000
1#
1)
#15000000
1"
0#
1(
0)
#20000000
1#
1)
0-
1.
#25000000
0#
0%
1&
0)
0+
1,
#30000000
1!
0"
1#
1'
0(
1)
1-
0.
#35000000
0#
1%
0&
0)
1+
0,
#40000000
1#
1)
#45000000
1"
0#
1(
0)
#50000000
1#
1)
0-
1.
#55000000
0#
0%
1&
0)
0+
1,
#60000000
0"
1#
1$
0(
1)
1*
