SequenceDetector1011/SequenceDetector.vhdl
library IEEE;
use IEEE.STD_LOGIC_1164.ALL;
use IEEE.NUMERIC_STD.ALL;

entity SequenceDetector is 
    Port( CLK, RST : IN STD_LOGIC;
          InputVal : IN STD_LOGIC;
          detected : OUT STD_LOGIC
          );
end SequenceDetector;

architecture BehavioralModel of SequenceDetector is

    type state is (S0, S1, S2, S3, S4);
    signal CurrentState : state;
    signal NextState : state;

begin
    process(CLK,RST)
    begin
        if RST = '1' then 
            CurrentState <= S0;
        elsif rising_edge(CLK) then
            CurrentState <= NextState;
        end if;
    end process;

    process(CurrentState, InputVal)
    begin
        case CurrentState is 
            when S0 =>
                if InputVal = '1' then
                    NextState <= S1;
                else
                    NextState <= S0;
                end if;

            when S1 =>
                if InputVal = '0' then
                    NextState <= S2;
                else
                    NextState <= S1;
                end if;
    
            when S2 =>
                if InputVal = '1' then
                    NextState <= S3;
                else
                    NextState <= S0;
                end if;


            when S3 =>
                if InputVal = '1' then
                    NextState <= S4;
                else
                    NextState <= S2;
                end if;


            when S4 =>
                if InputVal = '1' then
                    NextState <= S1;
                else
                    NextState <= S2;
                end if;
            end case;
        end process;

    detected <= '1' when CurrentState = S4 else '0';
     
end BehavioralModel;

SequenceDetector1011/SequenceDetector_tb.vhdl
library IEEE;
use IEEE.STD_LOGIC_1164.ALL;
use IEEE.NUMERIC_STD.ALL;

entity SequenceDetector_tb is 
end SequenceDetector_tb;

architecture Simulation1 of SequenceDetector_tb is

    signal CLK_tb, RST_tb, InputVal_tb, detected_tb : STD_LOGIC := '0';

begin
    SequenceDetector_Instance : entity work.SequenceDetector PORT MAP(CLK_tb, RST_tb, InputVal_tb, detected_tb);

    Clock_Process: process
    begin
        while now < 500 ns loop
            CLK_tb <= '0';
            wait for 5 ns;
            CLK_tb <= '1';
            wait for 5 ns;
        end loop;
        wait;
    end process;
    
    Stimulus_Process : process
    begin 
        RST_tb <= '1';
        wait for 10 ns;

        RST_tb <= '0';
        wait for 10 ns;

        InputVal_tb <= '1';
        wait for 10 ns;

        InputVal_tb <= '0';
        wait for 10 ns;

        InputVal_tb <= '1';
        wait for 10 ns;

        InputVal_tb <= '1';
        wait for 10 ns;

        InputVal_tb <= '0';
        wait for 10 ns;

        InputVal_tb <= '1';
        wait for 10 ns;

        InputVal_tb <= '0';
        wait for 10 ns;

        InputVal_tb <= '1';
        wait for 10 ns;

        InputVal_tb <= '1';
        wait for 10 ns;

        InputVal_tb <= '0';
        wait for 10 ns;

        InputVal_tb <= '1';
        wait for 10 ns;

        InputVal_tb <= '0';
        wait for 10 ns;

        wait;

    end process;

end Simulation1;

SequenceDetector1011/result.vcd
$date
  Fri Feb  9 22:39:02 2024
$end
$version
  GHDL v0
$end
$timescale
  1 fs
$end
$scope module standard $end
$upscope $end
$scope module std_logic_1164 $end
$upscope $end
$scope module numeric_std $end
$upscope $end
$scope module sequencedetector_tb $end
$var reg 1 ! clk_tb $end
$var reg 1 " rst_tb $end
$var reg 1 # inputval_tb $end
$var reg 1 $ detected_tb $end
$scope module sequencedetector_instance $end
$var reg 1 % clk $end
$var reg 1 & rst $end
$var reg 1 ' inputval $end
$var reg 1 ( detected $end
$comment currentstate is not handled $end
$comment nextstate is not handled $end
$upscope $end
$upscope $end
$enddefinitions $end
#0
0!
1"
0#
0$
0%
1&
0'
0(
#5000000
1!
1%
#10000000
0!
0"
0%
0&
#15000000
1!
1%
#20000000
0!
1#
0%
1'
#25000000
1!
1%
#30000000
0!
0#
0%
0'
#35000000
1!
1%
#40000000
0!
1#
0%
1'
#45000000
1!
1%
#50000000
0!
0%
#55000000
1!
1$
1%
1(
#60000000
0!
0#
0%
0'
#65000000
1!
0$
1%
0(
#70000000
0!
1#
0%
1'
#75000000
1!
1%
#80000000
0!
0#
0%
0'
#85000000
1!
1%
#90000000
0!
1#
0%
1'
#95000000
1!
1%
#100000000
0!
0%
#105000000
1!
1$
1%
1(
#110000000
0!
0#
0%
0'
#115000000
1!
0$
1%
0(
#120000000
0!
1#
0%
1'
#125000000
1!
1%
#130000000
0!
0#
0%
0'
