Structural_Question/and_or.vhdl
-- OR Gate
library IEEE;
use IEEE.std_logic_1164.all;

entity OR_GATE is
    port (
        X, Y: in std_logic;
        W: out std_logic
    );
end OR_GATE;

architecture OR_STRUCTURAL of OR_GATE is
begin
    process(X, Y)
    begin
        W <= X OR Y;
    end process;
end OR_STRUCTURAL;

-- AND Gate
library IEEE;
use IEEE.std_logic_1164.all;

entity AND_GATE is
    port (
        X, Y: in std_logic;
        W: out std_logic
    );
end AND_GATE;

architecture AND_STRUCTURAL of AND_GATE is
begin
    process(X, Y)
    begin
        W <= X or Y;
    end process;
end AND_STRUCTURAL;

-- Question Entity
library IEEE;
use IEEE.std_logic_1164.all;

entity QUESTION is
    port (
        A, B, C, D: in std_logic;
        Z: out std_logic
    );
end QUESTION;

architecture QUESTION_STRUCTURAL of QUESTION is
    component OR_GATE
        port (
            X, Y: in std_logic;
            W: out std_logic
        );
    end component;

    component AND_GATE
        port (
            X, Y: in std_logic;
            W: out std_logic
        );
    end component;

    signal E, F: std_logic;
begin
    U1: AND_GATE port map (X => A, Y => B, W => E);
    U2: AND_GATE port map (X => C, Y => D, W => F);
    U3: OR_GATE port map (X => E, Y => F, W => Z);
end QUESTION_STRUCTURAL;

Structural_Question/and_or_tb.vhdl
-- VHDL Testbench for StructuralLogic

library IEEE;
use IEEE.std_logic_1164.all;

entity and_or_tb is
end and_or_tb;

architecture behavior of and_or_tb is
    -- Declare the signals for the inputs and output
    signal A, B, C, D, Z : std_logic;
    
    -- Declare the component for the unit under test
    component QUESTION is
        port(
            A : in std_logic;
            B : in std_logic;
            C : in std_logic;
            D : in std_logic;
            Z : out std_logic
        );
    end component;

begin
    -- Instantiate the unit under question (UUT)
    UUT: QUESTION port map (
        A => A,
        B => B,
        C => C,
        D => D,
        Z => Z
    );

    -- Stimulus process
    stimulus_process: process
    begin
        -- Initialize inputs
        A <= '0'; B <= '0'; C <= '0'; D <= '0';
        wait for  10 ns;
        
        -- Test all possible input combinations
        for i in  0 to  15 loop
            A <= std_logic'val(i mod  2);
            B <= std_logic'val((i /  2) mod  2);
            C <= std_logic'val((i /  4) mod  2);
            D <= std_logic'val(i /  8);
            wait for  10 ns;
        end loop;

        -- Finish the simulation
        wait;
    end process;
end behavior;

Structural_Question/result.vcd
$date
  Mon Feb 19 08:39:30 2024
$end
$version
  GHDL v0
$end
$timescale
  1 fs
$end
$scope module standard $end
$upscope $end
$scope module std_logic_1164 $end
$upscope $end
$scope module and_or_tb $end
$var reg 1 ! a $end
$var reg 1 " b $end
$var reg 1 # c $end
$var reg 1 $ d $end
$var reg 1 % z $end
$scope module uut $end
$var reg 1 & a $end
$var reg 1 ' b $end
$var reg 1 ( c $end
$var reg 1 ) d $end
$var reg 1 * z $end
$var reg 1 + e $end
$var reg 1 , f $end
$scope module u1 $end
$var reg 1 - x $end
$var reg 1 . y $end
$var reg 1 / w $end
$upscope $end
$scope module u2 $end
$var reg 1 0 x $end
$var reg 1 1 y $end
$var reg 1 2 w $end
$upscope $end
$scope module u3 $end
$var reg 1 3 x $end
$var reg 1 4 y $end
$var reg 1 5 w $end
$upscope $end
$upscope $end
$upscope $end
$enddefinitions $end
#0
0!
0"
0#
0$
0%
0&
0'
0(
0)
0*
0+
0,
0-
0.
0/
00
01
02
03
04
05
#10000000
U!
U"
U#
U$
U%
U&
U'
U(
U)
U*
U+
U,
U-
U.
U/
U0
U1
U2
U3
U4
U5
#20000000
X!
X&
X-
#30000000
U!
X"
U&
X'
U-
X.
#40000000
X!
X&
X+
X-
X/
X3
#50000000
U!
U"
X#
U&
U'
X(
U+
U-
U.
U/
X0
U3
#60000000
X!
X&
X-
#70000000
U!
X"
U&
X'
U-
X.
#80000000
X!
X&
X+
X-
X/
X3
#90000000
U!
U"
U#
X$
U&
U'
U(
X)
U+
U-
U.
U/
U0
X1
U3
#100000000
X!
X&
X-
#110000000
U!
X"
U&
X'
U-
X.
#120000000
X!
X&
X+
X-
X/
X3
#130000000
U!
U"
X#
U&
U'
X(
U+
X,
U-
U.
U/
X0
X2
U3
X4
#140000000
X!
X&
X-
#150000000
U!
X"
U&
X'
U-
X.
#160000000
X!
X%
X&
X*
X+
X-
X/
X3
X5
